bitcoinutils/__init__.py
bitcoinutils/bech32.py
bitcoinutils/block.py
bitcoinutils/constants.py
bitcoinutils/hdwallet.py
bitcoinutils/keys.py
bitcoinutils/proxy.py
bitcoinutils/ripemd160.py
bitcoinutils/schnorr.py
bitcoinutils/script.py
bitcoinutils/setup.py
bitcoinutils/transactions.py
bitcoinutils/utils.py
my_bitcoin_utils-0.7.2.dist-info/LICENSE
my_bitcoin_utils-0.7.2.dist-info/METADATA
my_bitcoin_utils-0.7.2.dist-info/WHEEL
my_bitcoin_utils-0.7.2.dist-info/top_level.txt
my_bitcoin_utils-0.7.2.dist-info/RECORD
