Metadata-Version: 2.2
Name: my-bitcoin-utils
Version: 0.7.2
Summary: Bitcoin utility functions
Home-page: https://github.com/karask/python-bitcoin-utils
Author: Konstantinos Karasavvas
Author-email: kkarasavvas@gmail.com
License: MIT
Keywords: bitcoin library utilities tools
License-File: LICENSE
Requires-Dist: base58check<2.0,>=1.0.2
Requires-Dist: ecdsa==0.19.0
Requires-Dist: sympy<2.0,>=1.2
Requires-Dist: python-bitcoinrpc<2.0,>=1.0
Requires-Dist: hdwallet~=3.0
Dynamic: author
Dynamic: author-email
Dynamic: description
Dynamic: home-page
Dynamic: keywords
Dynamic: license
Dynamic: requires-dist
Dynamic: summary
